grucli/__init__.py
grucli/api.py
grucli/auth.py
grucli/chat_manager.py
grucli/commands.py
grucli/config.py
grucli/handlers.py
grucli/interrupt.py
grucli/main.py
grucli/permissions.py
grucli/stats.py
grucli/theme.py
grucli/tools.py
grucli/ui.py
grucli/sysprompts/main_sysprompt.txt
grucli-3.3.4.dist-info/licenses/LICENSE
grucli-3.3.4.dist-info/METADATA
grucli-3.3.4.dist-info/WHEEL
grucli-3.3.4.dist-info/entry_points.txt
grucli-3.3.4.dist-info/top_level.txt
grucli-3.3.4.dist-info/RECORD
