Metadata-Version: 2.4
Name: grucli
Version: 3.3.4
Summary: A command-line interface for interacting with local and remote LLMs.
Home-page: https://github.com/grufr/grucli
Author: grufr
Project-URL: Homepage, https://github.com/grufr/grucli
Project-URL: Bug Tracker, https://github.com/grufr/grucli/issues
Classifier: Programming Language :: Python :: 3
Classifier: License :: OSI Approved :: MIT License
Classifier: Operating System :: OS Independent
Requires-Python: >=3.6
License-File: LICENSE
Requires-Dist: requests
Requires-Dist: prompt_toolkit
Requires-Dist: cryptography
Requires-Dist: google-auth
Requires-Dist: google-auth-oauthlib
Dynamic: home-page
Dynamic: license-file
Dynamic: requires-python
